.gitignore
LICENSE
README.md
setup.py
django_idshost/__init__.py
django_idshost/forms.py
django_idshost/models.py
django_idshost/urls.py
django_idshost/views.py
django_idshost.egg-info/PKG-INFO
django_idshost.egg-info/SOURCES.txt
django_idshost.egg-info/dependency_links.txt
django_idshost.egg-info/requires.txt
django_idshost.egg-info/top_level.txt
django_idshost/auth/__init__.py
django_idshost/auth/idsauth.py
django_idshost/certificate/__init__.py
django_idshost/certificate/client.py
django_idshost/certificate/models.py
django_idshost/certificate/request.py
django_idshost/templates/api/logout_ids.html