Metadata-Version: 1.1
Name: django-idshost
Version: 0.1.0
Summary: Django app to interface with the ids infrastructure.
Home-page: https://github.com/optiflows/django-idshost
Author: Valentin Monte
Author-email: valentin.monte@optiflows.com
License: Apache License 2.0
Platform: UNKNOWN
Classifier: Environment :: Web Environment
Classifier: Framework :: Django
Classifier: Intended Audience :: Developers
Classifier: License :: OSI Approved :: Apache Software License
Classifier: Operating System :: OS Independent
Classifier: Programming Language :: Python
Classifier: Topic :: Software Development :: Libraries :: Python Modules
